MANIFEST.in
README.md
setup.py
nnvlp/__init__.py
nnvlp/__init__.pyc
nnvlp/alphabet.py
nnvlp/alphabet.pyc
nnvlp/embedding.sh
nnvlp/network.py
nnvlp/network.pyc
nnvlp/nnvlp.py
nnvlp/nnvlp.pyc
nnvlp/utils.py
nnvlp/utils.pyc
nnvlp.egg-info/PKG-INFO
nnvlp.egg-info/SOURCES.txt
nnvlp.egg-info/dependency_links.txt
nnvlp.egg-info/not-zip-safe
nnvlp.egg-info/requires.txt
nnvlp.egg-info/top_level.txt
nnvlp/pre-trained-model/chunk/alphabet_char.json
nnvlp/pre-trained-model/chunk/alphabet_label.json
nnvlp/pre-trained-model/chunk/alphabet_pos.json
nnvlp/pre-trained-model/chunk/config.ini
nnvlp/pre-trained-model/chunk/weights.npz
nnvlp/pre-trained-model/ner/alphabet_char.json
nnvlp/pre-trained-model/ner/alphabet_chunk.json
nnvlp/pre-trained-model/ner/alphabet_label.json
nnvlp/pre-trained-model/ner/alphabet_pos.json
nnvlp/pre-trained-model/ner/config.ini
nnvlp/pre-trained-model/ner/weights.npz
nnvlp/pre-trained-model/pos/alphabet_char.json
nnvlp/pre-trained-model/pos/alphabet_label.json
nnvlp/pre-trained-model/pos/config.ini
nnvlp/pre-trained-model/pos/weights.npz
nnvlp/test/__init__.py
nnvlp/test/test.py