Metadata-Version: 1.0
Name: nnvlp
Version: 0.1.7
Summary: Neural Network-Based Vietnamese Language Processing
Home-page: http://github.com/pth1993/nnvlp-package
Author: Hoang Pham
Author-email: phamthaihoang.hn@gmail.com
License: MIT
Platform: UNKNOWN
